magma_auth/__init__.py
magma_auth/auth.py
magma_auth/const.py
magma_auth/encryptor.py
magma_auth/utils.py
magma_auth-1.0.0.dist-info/licenses/LICENSE
magma_auth-1.0.0.dist-info/WHEEL
magma_auth-1.0.0.dist-info/METADATA
magma_auth-1.0.0.dist-info/RECORD
