Metadata-Version: 2.4
Name: magma-auth
Version: 1.0.0
Summary: MAGMA Indonesia Authentication
Keywords: magma,indonesia
Author-email: Martanto <martanto@live.com>, Devy Kamil Syahbana <devy.syahbana@gmail.com>, Syarif Abdul Manaf <riefmof@gmail.com>
Requires-Python: >=3.11
Classifier: License :: OSI Approved :: MIT License
Classifier: Operating System :: OS Independent
Classifier: Programming Language :: Python :: 3.11
Classifier: Programming Language :: Python :: 3.12
License-File: LICENSE
Requires-Dist: cryptography
Requires-Dist: pyjwt
Requires-Dist: cryptography ; extra == "dev"
Requires-Dist: pyjwt ; extra == "dev"
Requires-Dist: black[d] ; extra == "dev"
Requires-Dist: isort ; extra == "dev"
Project-URL: Homepage, https://github.com/martanto/magma-auth
Project-URL: Issues, https://github.com/martanto/magma-auth/issues
Provides-Extra: dev
